{
    "anime_id": 2277,
    "anime_name": "Re:Zero kara Hajimeru Isekai Seikatsu",
    "anime_slug": "rezero_kara_hajimeru_isekai_seikatsu",
    "anime_year": 2016,
    "anime_season": "Spring",
    "anime_synopsis": "",
    "anime_cover": "",
    "theme_id": 6890,
    "theme_type": "OP",
    "theme_sequence": 1,
    "theme_group": "",
    "theme_slug": "OP1",
    "entry_id": 8000,
    "entry_version": "",
    "entry_episodes": "2, 4, 6, 8, 10",
    "entry_notes": "",
    "video_id": 6943,
    "video_basename": "ReZero-OP1.webm",
    "video_filename": "ReZero-OP1",
    "video_path": "2016/Spring/ReZero-OP1.webm",
    "video_size": 65749494,
    "video_resolution": 1080,
    "video_source": "BD",
    "video_overlap": "None",
    "video_link": "https://animethemes.dev/video/ReZero-OP1.webm",
    "song_id": 6890,
    "song_title": "Redo",
    "video_filetype": "webm",
    "anime_filename": "ReZero"
}